edipy2/__init__.py
edipy2/edi2py.py
edipy2/func_aux_funx.py
edipy2/func_bath.py
edipy2/func_bath_fit.py
edipy2/func_io.py
edipy2/func_main.py
edipy2/func_parse_umatrix.py
edipy2/func_read_input.py
edipy2-4.0.0.dist-info/licenses/LICENSE.txt
edipy2-4.0.0.dist-info/METADATA
edipy2-4.0.0.dist-info/WHEEL
edipy2-4.0.0.dist-info/top_level.txt
edipy2-4.0.0.dist-info/RECORD
