Metadata-Version: 2.4
Name: edipy2
Version: 4.0.0
Summary: EDIpack2.0 Python API
Author-email: Lorenzo Crippa <crippa.lorenzo@gmail.com>, Adriano Amaricci <amaricci@sissa.it>
License: GPL-3.0-or-later
Project-URL: Source, https://github.com/edipack/edipy2.git
Keywords: edipack,edipy
Classifier: Intended Audience :: Science/Research
Classifier: Topic :: Scientific/Engineering :: Physics
Classifier: Programming Language :: Python :: 3
Classifier: Programming Language :: Python :: 3.10
Classifier: Programming Language :: Python :: 3.11
Classifier: Programming Language :: Python :: 3.12
Classifier: Programming Language :: Python :: 3.13
Requires-Python: >=3.8
License-File: LICENSE.txt
Requires-Dist: pkgconfig
Requires-Dist: numpy
Requires-Dist: mpi4py
Dynamic: license-file
